{
    "active-window.kak": {
        "branch": "master",
        "description": "Cursor is colored only in the active window",
        "homepage": null,
        "kakoune": "plugin",
        "owner": "greenfork",
        "repo": "active-window.kak",
        "rev": "988db69cfbb88bd741d089bb43b0be551693e7c1",
        "sha256": "1fv1cp9q212gamf9z2papl5xcl2w31fpcmbgdzbxcxdl1pvfsqp8",
        "type": "tarball",
        "url": "https://github.com/greenfork/active-window.kak/archive/988db69cfbb88bd741d089bb43b0be551693e7c1.tar.gz",
        "url_template": "https://github.com/<owner>/<repo>/archive/<rev>.tar.gz"
    },
    "comma": {
        "branch": "master",
        "description": null,
        "homepage": null,
        "owner": "Shopify",
        "repo": "comma",
        "rev": "4a62ec17e20ce0e738a8e5126b4298a73903b468",
        "sha256": "0n5a3rnv9qnnsrl76kpi6dmaxmwj1mpdd2g0b4n1wfimqfaz6gi1",
        "type": "tarball",
        "url": "https://github.com/Shopify/comma/archive/4a62ec17e20ce0e738a8e5126b4298a73903b468.tar.gz",
        "url_template": "https://github.com/<owner>/<repo>/archive/<rev>.tar.gz"
    },
    "fzf-tab": {
        "branch": "master",
        "description": "Replace zsh's default completion selection menu with fzf!",
        "homepage": "",
        "owner": "Aloxaf",
        "repo": "fzf-tab",
        "rev": "bc086fc38cfd680a90c694210fa5c5d88e3d1691",
        "sha256": "17in1byqxw8d6av30fpl4dlri2wma543aymp6a9xpibr64lmi373",
        "type": "tarball",
        "url": "https://github.com/Aloxaf/fzf-tab/archive/bc086fc38cfd680a90c694210fa5c5d88e3d1691.tar.gz",
        "url_template": "https://github.com/<owner>/<repo>/archive/<rev>.tar.gz"
    },
    "kak-subvert": {
        "branch": "master",
        "description": "Port of Tim Pope's vim abolish plugin coertion features to Kakoune",
        "homepage": "",
        "owner": "dmerejkowsky",
        "repo": "kak-subvert",
        "rev": "2aaf8b190692eb68d98facdd06cdf0446c79bd76",
        "sha256": "0ih278zxy1ppxjd6h36hkb5rc8kydsskwazrik5zdksi2yjbjlak",
        "type": "tarball",
        "url": "https://github.com/dmerejkowsky/kak-subvert/archive/2aaf8b190692eb68d98facdd06cdf0446c79bd76.tar.gz",
        "url_template": "https://github.com/<owner>/<repo>/archive/<rev>.tar.gz"
    },
    "kakoune-auto-percent": {
        "branch": "master",
        "description": "Enhance some primitives with bigger selections.",
        "homepage": "http://kakoune.org",
        "kakoune": "plugin",
        "owner": "Delapouite",
        "repo": "kakoune-auto-percent",
        "rev": "efca07df24074823425b5e56487c7a24c97111f5",
        "sha256": "1ff1fc6lqa42hia2nlyxqyg9bsbf8msi0x8vxyl6wpl5j2wvmpay",
        "type": "tarball",
        "url": "https://github.com/Delapouite/kakoune-auto-percent/archive/efca07df24074823425b5e56487c7a24c97111f5.tar.gz",
        "url_template": "https://github.com/<owner>/<repo>/archive/<rev>.tar.gz"
    },
    "kakoune-find": {
        "branch": "master",
        "description": "Find and replace on open buffers",
        "homepage": "",
        "kakoune": "plugin",
        "owner": "occivink",
        "repo": "kakoune-find",
        "rev": "cd6efb6da4ab7460ff8d87e27a4bf134b4632244",
        "sha256": "0y0bz65wmv9yswp63367w3fziy5k9ckzxy1m9bm1vn523a8ipc1f",
        "type": "tarball",
        "url": "https://github.com/occivink/kakoune-find/archive/cd6efb6da4ab7460ff8d87e27a4bf134b4632244.tar.gz",
        "url_template": "https://github.com/<owner>/<repo>/archive/<rev>.tar.gz"
    },
    "kakoune-palette": {
        "branch": "master",
        "description": "Preview face colors in kakoune",
        "homepage": "http://kakoune.org",
        "kakoune": "plugin",
        "owner": "Delapouite",
        "repo": "kakoune-palette",
        "rev": "052cab5f48578679d94717ed5f62429be9865d5d",
        "sha256": "1p9mpzx6i816pcw9sala2kvy0ky39kwccxgsf3y3bpw6m8pi6kby",
        "type": "tarball",
        "url": "https://github.com/Delapouite/kakoune-palette/archive/052cab5f48578679d94717ed5f62429be9865d5d.tar.gz",
        "url_template": "https://github.com/<owner>/<repo>/archive/<rev>.tar.gz"
    },
    "kakoune-snow": {
        "branch": "master",
        "description": "nightsense's snow colorscheme for Kakoune",
        "homepage": "",
        "kakoune": "colors",
        "owner": "caksoylar",
        "repo": "kakoune-snow",
        "rev": "35f81876bcaea061982396f8071b89528940ae61",
        "sha256": "14pndx88xm350a5kq8rha1k0436a3hl2qgfw9xkcfp1gkmzijx19",
        "type": "tarball",
        "url": "https://github.com/caksoylar/kakoune-snow/archive/35f81876bcaea061982396f8071b89528940ae61.tar.gz",
        "url_template": "https://github.com/<owner>/<repo>/archive/<rev>.tar.gz"
    },
    "kakoune-surround": {
        "branch": "master",
        "description": "Surround selection, Change/Delete surrounder",
        "homepage": null,
        "kakoune": "plugin",
        "owner": "h-youhei",
        "repo": "kakoune-surround",
        "rev": "efe74c6f434d1e30eff70d4b0d737f55bf6c5022",
        "sha256": "09fd7qhlsazf4bcl3z7xh9z0fklw69c5j32hminphihq74qrry6h",
        "type": "tarball",
        "url": "https://github.com/h-youhei/kakoune-surround/archive/efe74c6f434d1e30eff70d4b0d737f55bf6c5022.tar.gz",
        "url_template": "https://github.com/<owner>/<repo>/archive/<rev>.tar.gz"
    },
    "naersk": {
        "branch": "master",
        "description": "Build rust crates in Nix. No configuration, no code generation, no IFD. Sandbox friendly.",
        "homepage": "",
        "owner": "nmattia",
        "repo": "naersk",
        "rev": "e09c320446c5c2516d430803f7b19f5833781337",
        "sha256": "0k1pk2ixnxl6njjrgy750gm6m1nkkdsah383n3wp4ybrzacnav5h",
        "type": "tarball",
        "url": "https://github.com/nmattia/naersk/archive/e09c320446c5c2516d430803f7b19f5833781337.tar.gz",
        "url_template": "https://github.com/<owner>/<repo>/archive/<rev>.tar.gz"
    },
    "niv": {
        "branch": "master",
        "description": "Easy dependency management for Nix projects",
        "homepage": "https://github.com/nmattia/niv",
        "owner": "nmattia",
        "repo": "niv",
        "rev": "e0ca65c81a2d7a4d82a189f1e23a48d59ad42070",
        "sha256": "1pq9nh1d8nn3xvbdny8fafzw87mj7gsmp6pxkdl65w2g18rmcmzx",
        "type": "tarball",
        "url": "https://github.com/nmattia/niv/archive/e0ca65c81a2d7a4d82a189f1e23a48d59ad42070.tar.gz",
        "url_template": "https://github.com/<owner>/<repo>/archive/<rev>.tar.gz"
    },
    "nixos-hardware": {
        "branch": "master",
        "description": "A collection of NixOS modules covering hardware quirks.",
        "homepage": "",
        "owner": "NixOS",
        "repo": "nixos-hardware",
        "rev": "41775780a0b6b32b3d32dcc32bb9bc6df809062d",
        "sha256": "0121bmdga42zkn4y3wsy71b5lglzn180q7vmxaprqp5lvr27v8ik",
        "type": "tarball",
        "url": "https://github.com/NixOS/nixos-hardware/archive/41775780a0b6b32b3d32dcc32bb9bc6df809062d.tar.gz",
        "url_template": "https://github.com/<owner>/<repo>/archive/<rev>.tar.gz"
    },
    "nixos-unstable": {
        "branch": "nixos-unstable",
        "description": "Nix Packages collection",
        "homepage": "",
        "owner": "NixOS",
        "repo": "nixpkgs",
        "rev": "036dc0c709650e0c833822307af801f576d67273",
        "sha256": "0pnrygs6xf7id63zi17pq5379hfppwbb5cfazhypcqz6l3dfk00g",
        "type": "tarball",
        "url": "https://github.com/NixOS/nixpkgs/archive/036dc0c709650e0c833822307af801f576d67273.tar.gz",
        "url_template": "https://github.com/<owner>/<repo>/archive/<rev>.tar.gz"
    },
    "nixpkgs": {
        "branch": "nixpkgs-unstable",
        "description": "A read-only mirror of NixOS/nixpkgs tracking the released channels. Send issues and PRs to",
        "homepage": "https://github.com/NixOS/nixpkgs",
        "owner": "NixOS",
        "repo": "nixpkgs-channels",
        "rev": "502845c3e31ef3de0e424f3fcb09217df2ce6df6",
        "sha256": "0fcqpsy6y7dgn0y0wgpa56gsg0b0p8avlpjrd79fp4mp9bl18nda",
        "type": "tarball",
        "url": "https://github.com/NixOS/nixpkgs-channels/archive/502845c3e31ef3de0e424f3fcb09217df2ce6df6.tar.gz",
        "url_template": "https://github.com/<owner>/<repo>/archive/<rev>.tar.gz"
    },
    "prelude.kak": {
        "branch": "master",
        "description": "Prelude of shell blocks for Kakoune",
        "homepage": "https://kakoune.org",
        "kakoune": "plugin",
        "owner": "alexherbo2",
        "repo": "prelude.kak",
        "rev": "5dbdc020c546032885c1fdb463e366cc89fc15ad",
        "sha256": "1pncr8azqvl2z9yvzhc68p1s9fld8cvak8yz88zgrp5ypx2cxl8c",
        "type": "tarball",
        "url": "https://github.com/alexherbo2/prelude.kak/archive/5dbdc020c546032885c1fdb463e366cc89fc15ad.tar.gz",
        "url_template": "https://github.com/<owner>/<repo>/archive/<rev>.tar.gz"
    },
    "shellcheck.kak": {
        "branch": "master",
        "description": "ShellCheck integration for Kakoune",
        "homepage": null,
        "kakoune": "plugin",
        "owner": "whereswaldon",
        "repo": "shellcheck.kak",
        "rev": "4e633978c119bbb71f215828f7b59cea71a2c5a4",
        "sha256": "1629jh4387ybl2iizyqc7k7r1n1rx2ljg5acn294z2jqfxg2n6mj",
        "type": "tarball",
        "url": "https://github.com/whereswaldon/shellcheck.kak/archive/4e633978c119bbb71f215828f7b59cea71a2c5a4.tar.gz",
        "url_template": "https://github.com/<owner>/<repo>/archive/<rev>.tar.gz"
    },
    "similar-sort": {
        "sha256": "0sykdp82cby1ikw4pxzcp1hrhj51dwz0zpprcsj03hhsyg0c1j7b",
        "type": "tarball",
        "url": "https://git.bytes.zone/brian/similar-sort/archive/301de2b5f83aba77a14b4df33347e8157de4f9ca.tar.gz",
        "url_template": "https://git.bytes.zone/brian/similar-sort/archive/<version>.tar.gz",
        "version": "301de2b5f83aba77a14b4df33347e8157de4f9ca"
    },
    "smarttab.kak": {
        "branch": "master",
        "description": "Automatic handling different styles of indentation and alignment. Mirror of https://gitlab.com/andreyorst/smarttab.kak",
        "homepage": "",
        "kakoune": "plugin",
        "owner": "andreyorst",
        "repo": "smarttab.kak",
        "rev": "1dd3f33c4f65da5c13aee5d44b2e77399595830f",
        "sha256": "0g49k47ggppng95nwanv2rqmcfsjsgy3z1764wrl5b49h9wifhg2",
        "type": "tarball",
        "url": "https://github.com/andreyorst/smarttab.kak/archive/1dd3f33c4f65da5c13aee5d44b2e77399595830f.tar.gz",
        "url_template": "https://github.com/<owner>/<repo>/archive/<rev>.tar.gz"
    },
    "tree-grepper": {
        "branch": "main",
        "repo": "https://git.bytes.zone/brian/tree-grepper.git",
        "rev": "29b957d8c6684af77b03fc51b13d0bd99aa85cbb",
        "type": "git"
    },
    "tug": {
        "branch": "master",
        "description": "Unix commands for the kakoune editor",
        "homepage": null,
        "kakoune": "plugin",
        "owner": "matthias-margush",
        "repo": "tug",
        "rev": "23adaadb795af2d86dcb3daf7af3ebe12e932441",
        "sha256": "0qldzh3gr3m7sa1hibbmf1br5lgiqwn84ggm75iin113zc67avbi",
        "type": "tarball",
        "url": "https://github.com/matthias-margush/tug/archive/23adaadb795af2d86dcb3daf7af3ebe12e932441.tar.gz",
        "url_template": "https://github.com/<owner>/<repo>/archive/<rev>.tar.gz"
    }
}
